LICENSE.txt
MANIFEST.in
README.MD
pyproject.toml
setup.cfg
setup.py
tests/test_analytics_google_analytics_id.py
tests/test_analytics_google_tag_manager_id.py
tests/test_content.py
tests/test_forms.py
tests/test_generic_selectors.py
tests/test_google_search_features.py
tests/test_headings.py
tests/test_images.py
tests/test_links.py
tests/test_meta_tags.py
tests/test_open_graph_tags.py
tests/test_structured_data_json_ld.py
webextractionhelper/__init__.py
webextractionhelper/selectors.py
webextractionhelper.egg-info/PKG-INFO
webextractionhelper.egg-info/SOURCES.txt
webextractionhelper.egg-info/dependency_links.txt
webextractionhelper.egg-info/requires.txt
webextractionhelper.egg-info/top_level.txt