Metadata-Version: 2.4
Name: webextractionhelper
Version: 0.1.1
Summary: A comprehensive web scraping helper package with XPath selectors, regex patterns, and CSS selectors
Home-page: https://github.com/Artistotle-ai/webextractionhelper
Download-URL: https://github.com/Artistotle-ai/webextractionhelper/archive/refs/tags/v0.1.1.tar.gz
Author: Jens Verneuer
Author-email: Jens Verneuer <Jens@Aristotle.ventures>
Maintainer-email: Jens Verneuer <Jens@Aristotle.ventures>
License: CC-BY-SA-4.0
Project-URL: Homepage, https://github.com/Artistotle-ai/webextractionhelper
Project-URL: Documentation, https://github.com/Artistotle-ai/webextractionhelper#readme
Project-URL: Repository, https://github.com/Artistotle-ai/webextractionhelper
Project-URL: Issues, https://github.com/Artistotle-ai/webextractionhelper/issues
Keywords: web scraping,xpath,css selectors,regex,google search,serp
Classifier: Development Status :: 3 - Alpha
Classifier: Intended Audience :: Developers
Classifier: Operating System :: OS Independent
Classifier: Programming Language :: Python :: 3
Classifier: Programming Language :: Python :: 3.7
Classifier: Programming Language :: Python :: 3.8
Classifier: Programming Language :: Python :: 3.9
Classifier: Programming Language :: Python :: 3.10
Classifier: Programming Language :: Python :: 3.11
Classifier: Programming Language :: Python :: 3.12
Classifier: Topic :: Internet :: WWW/HTTP
Classifier: Topic :: Software Development :: Libraries :: Python Modules
Classifier: Topic :: Text Processing :: Markup :: HTML
Requires-Python: >=3.7
License-File: LICENSE.txt
Requires-Dist: lxml>=4.6.0
Provides-Extra: dev
Requires-Dist: pytest>=6.0; extra == "dev"
Requires-Dist: pytest-cov>=2.0; extra == "dev"
Requires-Dist: black>=21.0; extra == "dev"
Requires-Dist: flake8>=3.8; extra == "dev"
Dynamic: author
Dynamic: download-url
Dynamic: home-page
Dynamic: license-file
Dynamic: requires-python
